AUTHORS
CHANGELOG.md
LICENSE
MANIFEST.in
README.md
setup.py
docgen/__init__.py
docgen/__main__.py
docgen/types.py
docgen/util.py
docgen.egg-info/PKG-INFO
docgen.egg-info/SOURCES.txt
docgen.egg-info/dependency_links.txt
docgen.egg-info/entry_points.txt
docgen.egg-info/not-zip-safe
docgen.egg-info/top_level.txt
docs/types.md
docs/util.md