Metadata-Version: 1.1
Name: docgen
Version: 0.1.1
Summary: A markdown documentation generator for Python
Home-page: https://bitbucket.org/bkvaluemeal/docgen
Author: Justin Willis
Author-email: sirJustin.Willis@gmail.com
License: ISC License
Keywords: markdown documentation generator
Platform: UNKNOWN
Classifier: Development Status :: 3 - Alpha
Classifier: Environment :: Console
Classifier: Intended Audience :: Developers
Classifier: License :: OSI Approved :: ISC License (ISCL)
Classifier: Operating System :: OS Independent
Classifier: Programming Language :: Python :: 3
Classifier: Topic :: Documentation
